swingtrend/Swing.py
swingtrend/__init__.py
swingtrend-2.0.3.dist-info/METADATA
swingtrend-2.0.3.dist-info/WHEEL
swingtrend-2.0.3.dist-info/licenses/LICENSE
swingtrend-2.0.3.dist-info/RECORD
