Metadata-Version: 2.4
Name: swingtrend
Version: 2.0.3
Summary: A mechanical approach to determine the trend of a stock along with breakout and reversal levels.
Project-URL: Bug Tracker, https://github.com/BennyThadikaran/SwingTrend/issues
Project-URL: Homepage, https://github.com/BennyThadikaran/SwingTrend
Author: Benny Thadikaran
License-File: LICENSE
Keywords: finance,python3,stock-markets,technical-analysis,technical-indicators,trend-detection
Classifier: Intended Audience :: Developers
Classifier: Intended Audience :: Financial and Insurance Industry
Classifier: License :: OSI Approved :: GNU General Public License v3 (GPLv3)
Classifier: Natural Language :: English
Classifier: Operating System :: OS Independent
Classifier: Programming Language :: Python :: 3 :: Only
Classifier: Programming Language :: Python :: 3.8
Classifier: Programming Language :: Python :: 3.9
Classifier: Programming Language :: Python :: 3.10
Classifier: Programming Language :: Python :: 3.11
Classifier: Programming Language :: Python :: 3.12
Classifier: Programming Language :: Python :: 3.13
Classifier: Programming Language :: Python :: 3.14
Classifier: Topic :: Office/Business :: Financial :: Investment
Classifier: Topic :: Software Development :: Libraries
Classifier: Topic :: Software Development :: Libraries :: Python Modules
Requires-Python: >=3.8
